logair/__init__.py
logair/logger.py
logair-1.0.8.dist-info/METADATA
logair-1.0.8.dist-info/WHEEL
logair-1.0.8.dist-info/top_level.txt
logair-1.0.8.dist-info/RECORD
