Metadata-Version: 2.1
Name: logair
Version: 1.0.8
Requires-Python: >=3.8
Requires-Dist: loguru>=0.7.3
